<?xml version="1.0" encoding="utf-8"?>
<strings>
  <string key="SEOAssistant" value="SEO Assistant" />
  <string key="SEOAssistant.ToolTip" value="Search engine optimization" />
  <string key="IntroText" value="Generate a page preview to compute the SEO indication." />
  <string key="TabResult" value="Result" />
  <string key="TabKeywords" value="Keywords" />
  <string key="ResultHeading" value="Keywords found in page preview:" />
  <string key="NoKeywordsWarning" value="No keywords configured." />
  <string key="isInTitle" value="In title" />
  <string key="isInURL" value="In URL" />
  <string key="isInMenuTitle" value="In menu title" />
  <string key="isInDescription" value="In description" />
  <string key="isInHeading" value="In heading" />
  <string key="isInContent" value="In content" />
  <string key="NoKeywords" value="No keywords found in page preview" />
	<string key="IncorrectHtml" value="Failed to analyze the keywords because the markup is not valid" />
  <string key="AddKeywordInputPlaceholder" value="Add SEO word ..." />
</strings>